bskillskit/__init__.py
bskillskit/file_reader.py
bskillskit/skills_error_enum.py
bskillskit/skills_writer.py
bskillskit-0.8.2.dist-info/DESCRIPTION.rst
bskillskit-0.8.2.dist-info/METADATA
bskillskit-0.8.2.dist-info/RECORD
bskillskit-0.8.2.dist-info/WHEEL
bskillskit-0.8.2.dist-info/metadata.json
bskillskit-0.8.2.dist-info/top_level.txt
