Metadata-Version: 2.0
Name: bskillskit
Version: 0.8.2
Summary: It is a helper tool with reference to box skills. It is not official.
Home-page: https://github.com/KentaroAOKI/bskillskit
Author: Kentaro Aoki
Author-email: UNKNOWN
License: UNKNOWN
Keywords: bskillskit
Platform: UNKNOWN
Classifier: License :: OSI Approved :: Apache Software License
Classifier: Programming Language :: Python :: 3.4
Classifier: Programming Language :: Python :: 3.5
Classifier: Programming Language :: Python :: 3.6
Requires-Dist: boxsdk
